fibertrace/__init__.py
fibertrace/log.py
fibertrace-0.1.5.dist-info/METADATA
fibertrace-0.1.5.dist-info/WHEEL
fibertrace-0.1.5.dist-info/top_level.txt
fibertrace-0.1.5.dist-info/RECORD
