Metadata-Version: 2.1
Name: fibertrace
Version: 0.1.5
Summary: A library for simple logging
Home-page: https://github.com/bytesentinel-io/fibertrace.py
Author: ByteSentinel.io
Author-email: dev@bytesentinel.io
Classifier: Programming Language :: Python :: 3
Classifier: License :: OSI Approved :: MIT License
Classifier: Operating System :: OS Independent
Requires-Python: >=3.7
